[
  {
    "name": "Das coole Produkt",
    "brand": "Boss",
    "color": "Coool",
    "size": "Gigantisch",
    "weight": 99.99,
    "description": "riesig",
    "category": "Nicht nötig",
    "prices": [
      { "validFrom": "07.05.2021", "validTo": "07.05.2022", "price": "902.00" }
    ],
    "discounted": true,
    "discountAmount": 20,
    "stock": 117,
    "packagingSize": "",
    "packagingWeight": "Gewicht7",
    "discontinued": false,
    "modelnumber": "kp3414v1li3932fq",
    "_id": "646f758a8f5647cedd9185b1"
  },
  {
    "name": "Geschirrspüler 200",
    "brand": "Bosch",
    "color": "Silber",
    "size": "Größe 8",
    "weight": 41.85,
    "description": "Geräuscharm",
    "category": "Geschirrspüler",
    "prices": [
      { "validFrom": "07.05.2020", "validTo": "07.05.2021", "price": "675.56" },
      { "validFrom": "07.05.2021", "validTo": "07.05.2022", "price": "902.00" }
    ],
    "discounted": true,
    "discountAmount": 20,
    "stock": 117,
    "packagingSize": "",
    "packagingWeight": "Gewicht 7",
    "discontinued": false,
    "modelnumber": "54r12opklhdhl5ug",
    "_id": "645c9ffb7d433216f16d7c90"
  },
  {
    "name": "Mikrowelle 199",
    "brand": "Bosch",
    "color": "Blau",
    "size": "Größe 2",
    "weight": 8.44,
    "description": "Hohe Energieeffizienz",
    "category": "Mikrowelle",
    "prices": [
      { "validFrom": "07.05.2020", "validTo": "07.05.2021", "price": "506.66" },
      { "validFrom": "07.05.2021", "validTo": "07.05.2022", "price": "442.94" }
    ],
    "discounted": false,
    "discountAmount": 30,
    "stock": 993,
    "packagingSize": "",
    "packagingWeight": "Gewicht 8",
    "discontinued": false,
    "modelnumber": "54r12opklhdhl5uf",
    "_id": "645c9ffb7d433216f16d7c8f"
  },
  {
    "name": "Kühlschrank 198",
    "brand": "LG",
    "color": "Rot",
    "size": "Größe 6",
    "weight": 48.06,
    "description": "Viel Platz",
    "category": "Kühlschrank",
    "prices": [
      {
        "validFrom": "07.05.2020",
        "validTo": "07.05.2021",
        "price": "1346.22"
      },
      { "validFrom": "07.05.2021", "validTo": "07.05.2022", "price": "396.56" }
    ],
    "discounted": true,
    "discountAmount": 10,
    "stock": 117,
    "packagingSize": "",
    "packagingWeight": "Gewicht 6",
    "discontinued": false,
    "modelnumber": "54r12opklhdhl5ue",
    "_id": "645c9ffb7d433216f16d7c8e"
  },
  {
    "name": "Mikrowelle 197",
    "brand": "Samsung",
    "color": "Blau",
    "size": "Größe 5",
    "weight": 23.57,
    "description": "Viel Platz",
    "category": "Mikrowelle",
    "prices": [
      { "validFrom": "07.05.2020", "validTo": "07.05.2021", "price": "999.71" },
      { "validFrom": "07.05.2021", "validTo": "07.05.2022", "price": "310.21" }
    ],
    "discounted": true,
    "discountAmount": 30,
    "stock": 488,
    "packagingSize": "",
    "packagingWeight": "Gewicht 3",
    "discontinued": false,
    "modelnumber": "54r12opklhdhl5ud",
    "_id": "645c9ffb7d433216f16d7c8d"
  },
  {
    "name": "Geschirrspüler 196",
    "brand": "AEG",
    "color": "Silber",
    "size": "Größe 2",
    "weight": 49.01,
    "description": "Einfache Bedienung",
    "category": "Geschirrspüler",
    "prices": [
      {
        "validFrom": "07.05.2020",
        "validTo": "07.05.2021",
        "price": "1488.75"
      },
      { "validFrom": "07.05.2021", "validTo": "07.05.2022", "price": "308.42" }
    ],
    "discounted": false,
    "discountAmount": 20,
    "stock": 629,
    "packagingSize": "",
    "packagingWeight": "Gewicht 4",
    "discontinued": false,
    "modelnumber": "54r12opklhdhl5uc",
    "_id": "645c9ffb7d433216f16d7c8c"
  },
  {
    "name": "Trockner 195",
    "brand": "Samsung",
    "color": "Blau",
    "size": "Größe 4",
    "weight": 23.18,
    "description": "Hohe Energieeffizienz",
    "category": "Trockner",
    "prices": [
      {
        "validFrom": "07.05.2020",
        "validTo": "07.05.2021",
        "price": "1389.49"
      },
      { "validFrom": "07.05.2021", "validTo": "07.05.2022", "price": "434.63" }
    ],
    "discounted": true,
    "discountAmount": 30,
    "stock": 470,
    "packagingSize": "",
    "packagingWeight": "Gewicht 7",
    "discontinued": false,
    "modelnumber": "54r12opklhdhl5ub",
    "_id": "645c9ffb7d433216f16d7c8b"
  },
  {
    "name": "Trockner 194",
    "brand": "Miele",
    "color": "Blau",
    "size": "Größe 9",
    "weight": 3.26,
    "description": "Viel Platz",
    "category": "Trockner",
    "prices": [
      {
        "validFrom": "07.05.2020",
        "validTo": "07.05.2021",
        "price": "1269.64"
      },
      { "validFrom": "07.05.2021", "validTo": "07.05.2022", "price": "793.66" }
    ],
    "discounted": true,
    "discountAmount": 30,
    "stock": 303,
    "packagingSize": "",
    "packagingWeight": "Gewicht 5",
    "discontinued": false,
    "modelnumber": "54r12opklhdhl5ua",
    "_id": "645c9ffb7d433216f16d7c8a"
  },
  {
    "name": "Geschirrspüler 193",
    "brand": "Siemens",
    "color": "Rot",
    "size": "Größe 10",
    "weight": 11.33,
    "description": "Hohe Energieeffizienz",
    "category": "Geschirrspüler",
    "prices": [
      { "validFrom": "07.05.2020", "validTo": "07.05.2021", "price": "589.35" },
      { "validFrom": "07.05.2021", "validTo": "07.05.2022", "price": "276.93" }
    ],
    "discounted": true,
    "discountAmount": 20,
    "stock": 513,
    "packagingSize": "",
    "packagingWeight": "Gewicht 1",
    "discontinued": false,
    "modelnumber": "54r12opklhdhl5u9",
    "_id": "645c9ffb7d433216f16d7c89"
  },
  {
    "name": "Kühlschrank 192",
    "brand": "Siemens",
    "color": "Weiß",
    "size": "Größe 6",
    "weight": 39.21,
    "description": "Geräuscharm",
    "category": "Kühlschrank",
    "prices": [
      {
        "validFrom": "07.05.2020",
        "validTo": "07.05.2021",
        "price": "1137.52"
      },
      { "validFrom": "07.05.2021", "validTo": "07.05.2022", "price": "538.31" }
    ],
    "discounted": false,
    "discountAmount": 30,
    "stock": 695,
    "packagingSize": "",
    "packagingWeight": "Gewicht 2",
    "discontinued": false,
    "modelnumber": "54r12opklhdhl5u8",
    "_id": "645c9ffb7d433216f16d7c88"
  },
  {
    "name": "Kühlschrank 191",
    "brand": "LG",
    "color": "Schwarz",
    "size": "Größe 5",
    "weight": 4.23,
    "description": "Viel Platz",
    "category": "Kühlschrank",
    "prices": [
      { "validFrom": "07.05.2020", "validTo": "07.05.2021", "price": "830.98" },
      { "validFrom": "07.05.2021", "validTo": "07.05.2022", "price": "238.69" }
    ],
    "discounted": true,
    "discountAmount": 30,
    "stock": 711,
    "packagingSize": "",
    "packagingWeight": "Gewicht 7",
    "discontinued": false,
    "modelnumber": "54r12opklhdhl5u7",
    "_id": "645c9ffb7d433216f16d7c87"
  },
  {
    "name": "Waschmaschine 190",
    "brand": "Bosch",
    "color": "Rot",
    "size": "Größe 4",
    "weight": 14.88,
    "description": "Hohe Energieeffizienz",
    "category": "Waschmaschine",
    "prices": [
      { "validFrom": "07.05.2020", "validTo": "07.05.2021", "price": "856.44" },
      { "validFrom": "07.05.2021", "validTo": "07.05.2022", "price": "557.30" }
    ],
    "discounted": true,
    "discountAmount": 10,
    "stock": 302,
    "packagingSize": "",
    "packagingWeight": "Gewicht 9",
    "discontinued": false,
    "modelnumber": "54r12opklhdhl5u6",
    "_id": "645c9ffb7d433216f16d7c86"
  },
  {
    "name": "Waschmaschine 189",
    "brand": "Siemens",
    "color": "Weiß",
    "size": "Größe 7",
    "weight": 40.11,
    "description": "Viel Platz",
    "category": "Waschmaschine",
    "prices": [
      { "validFrom": "07.05.2020", "validTo": "07.05.2021", "price": "558.80" },
      { "validFrom": "07.05.2021", "validTo": "07.05.2022", "price": "438.95" }
    ],
    "discounted": false,
    "discountAmount": 30,
    "stock": 129,
    "packagingSize": "",
    "packagingWeight": "Gewicht 3",
    "discontinued": false,
    "modelnumber": "54r12opklhdhl5u5",
    "_id": "645c9ffb7d433216f16d7c85"
  },
  {
    "name": "Ofen 188",
    "brand": "LG",
    "color": "Schwarz",
    "size": "Größe 10",
    "weight": 36.18,
    "description": "Geräuscharm",
    "category": "Ofen",
    "prices": [
      { "validFrom": "07.05.2020", "validTo": "07.05.2021", "price": "879.05" },
      { "validFrom": "07.05.2021", "validTo": "07.05.2022", "price": "494.88" }
    ],
    "discounted": true,
    "discountAmount": 10,
    "stock": 673,
    "packagingSize": "",
    "packagingWeight": "Gewicht 1",
    "discontinued": false,
    "modelnumber": "54r12opklhdhl5u4",
    "_id": "645c9ffb7d433216f16d7c84"
  },
  {
    "name": "Geschirrspüler 187",
    "brand": "Bosch",
    "color": "Blau",
    "size": "Größe 5",
    "weight": 8.93,
    "description": "Einfache Bedienung",
    "category": "Geschirrspüler",
    "prices": [
      { "validFrom": "07.05.2020", "validTo": "07.05.2021", "price": "515.85" },
      { "validFrom": "07.05.2021", "validTo": "07.05.2022", "price": "870.84" }
    ],
    "discounted": false,
    "discountAmount": 10,
    "stock": 772,
    "packagingSize": "",
    "packagingWeight": "Gewicht 6",
    "discontinued": false,
    "modelnumber": "54r12opklhdhl5u3",
    "_id": "645c9ffb7d433216f16d7c83"
  },
  {
    "name": "Geschirrspüler 186",
    "brand": "Miele",
    "color": "Rot",
    "size": "Größe 1",
    "weight": 29.76,
    "description": "Einfache Bedienung",
    "category": "Geschirrspüler",
    "prices": [
      { "validFrom": "07.05.2020", "validTo": "07.05.2021", "price": "718.35" },
      { "validFrom": "07.05.2021", "validTo": "07.05.2022", "price": "393.00" }
    ],
    "discounted": false,
    "discountAmount": 10,
    "stock": 786,
    "packagingSize": "",
    "packagingWeight": "Gewicht 6",
    "discontinued": false,
    "modelnumber": "54r12opklhdhl5u2",
    "_id": "645c9ffb7d433216f16d7c82"
  },
  {
    "name": "Trockner 185",
    "brand": "Bosch",
    "color": "Blau",
    "size": "Größe 2",
    "weight": 11.98,
    "description": "Geräuscharm",
    "category": "Trockner",
    "prices": [
      { "validFrom": "07.05.2020", "validTo": "07.05.2021", "price": "435.60" },
      { "validFrom": "07.05.2021", "validTo": "07.05.2022", "price": "645.50" }
    ],
    "discounted": false,
    "discountAmount": 30,
    "stock": 435,
    "packagingSize": "",
    "packagingWeight": "Gewicht 8",
    "discontinued": false,
    "modelnumber": "54r12opklhdhl5u1",
    "_id": "645c9ffb7d433216f16d7c81"
  },
  {
    "name": "Kühlschrank 184",
    "brand": "Samsung",
    "color": "Blau",
    "size": "Größe 7",
    "weight": 37.85,
    "description": "Geräuscharm",
    "category": "Kühlschrank",
    "prices": [
      { "validFrom": "07.05.2020", "validTo": "07.05.2021", "price": "491.96" },
      { "validFrom": "07.05.2021", "validTo": "07.05.2022", "price": "769.54" }
    ],
    "discounted": true,
    "discountAmount": 30,
    "stock": 64,
    "packagingSize": "",
    "packagingWeight": "Gewicht 1",
    "discontinued": false,
    "modelnumber": "54r12opklhdhl5u0",
    "_id": "645c9ffb7d433216f16d7c80"
  },
  {
    "name": "Trockner 183",
    "brand": "Samsung",
    "color": "Weiß",
    "size": "Größe 5",
    "weight": 13.32,
    "description": "Hohe Energieeffizienz",
    "category": "Trockner",
    "prices": [
      { "validFrom": "07.05.2020", "validTo": "07.05.2021", "price": "477.76" },
      { "validFrom": "07.05.2021", "validTo": "07.05.2022", "price": "652.67" }
    ],
    "discounted": false,
    "discountAmount": 30,
    "stock": 325,
    "packagingSize": "",
    "packagingWeight": "Gewicht 1",
    "discontinued": false,
    "modelnumber": "54r12opklhdhl5tz",
    "_id": "645c9ffb7d433216f16d7c7f"
  },
  {
    "name": "Waschmaschine 182",
    "brand": "Bosch",
    "color": "Weiß",
    "size": "Größe 1",
    "weight": 12.94,
    "description": "Einfache Bedienung",
    "category": "Waschmaschine",
    "prices": [
      { "validFrom": "07.05.2020", "validTo": "07.05.2021", "price": "501.30" },
      { "validFrom": "07.05.2021", "validTo": "07.05.2022", "price": "362.56" }
    ],
    "discounted": true,
    "discountAmount": 30,
    "stock": 881,
    "packagingSize": "",
    "packagingWeight": "Gewicht 9",
    "discontinued": false,
    "modelnumber": "54r12opklhdhl5ty",
    "_id": "645c9ffb7d433216f16d7c7e"
  },
  {
    "name": "Waschmaschine 181",
    "brand": "Miele",
    "color": "Weiß",
    "size": "Größe 8",
    "weight": 29.96,
    "description": "Hohe Energieeffizienz",
    "category": "Waschmaschine",
    "prices": [
      { "validFrom": "07.05.2020", "validTo": "07.05.2021", "price": "382.34" },
      { "validFrom": "07.05.2021", "validTo": "07.05.2022", "price": "691.46" }
    ],
    "discounted": false,
    "discountAmount": 10,
    "stock": 779,
    "packagingSize": "",
    "packagingWeight": "Gewicht 3",
    "discontinued": false,
    "modelnumber": "54r12opklhdhl5tx",
    "_id": "645c9ffb7d433216f16d7c7d"
  },
  {
    "name": "Trockner 180",
    "brand": "Miele",
    "color": "Blau",
    "size": "Größe 4",
    "weight": 41.9,
    "description": "Einfache Bedienung",
    "category": "Trockner",
    "prices": [
      {
        "validFrom": "07.05.2020",
        "validTo": "07.05.2021",
        "price": "1109.04"
      },
      { "validFrom": "07.05.2021", "validTo": "07.05.2022", "price": "667.19" }
    ],
    "discounted": true,
    "discountAmount": 10,
    "stock": 560,
    "packagingSize": "",
    "packagingWeight": "Gewicht 10",
    "discontinued": false,
    "modelnumber": "54r12opklhdhl5tw",
    "_id": "645c9ffb7d433216f16d7c7c"
  },
  {
    "name": "Trockner 179",
    "brand": "Miele",
    "color": "Silber",
    "size": "Größe 1",
    "weight": 12.96,
    "description": "Einfache Bedienung",
    "category": "Trockner",
    "prices": [
      { "validFrom": "07.05.2020", "validTo": "07.05.2021", "price": "227.60" },
      { "validFrom": "07.05.2021", "validTo": "07.05.2022", "price": "911.90" }
    ],
    "discounted": true,
    "discountAmount": 20,
    "stock": 690,
    "packagingSize": "",
    "packagingWeight": "Gewicht 9",
    "discontinued": false,
    "modelnumber": "54r12opklhdhl5tv",
    "_id": "645c9ffb7d433216f16d7c7b"
  },
  {
    "name": "Waschmaschine 178",
    "brand": "Samsung",
    "color": "Schwarz",
    "size": "Größe 1",
    "weight": 44.27,
    "description": "Hohe Energieeffizienz",
    "category": "Waschmaschine",
    "prices": [
      { "validFrom": "07.05.2020", "validTo": "07.05.2021", "price": "961.80" },
      { "validFrom": "07.05.2021", "validTo": "07.05.2022", "price": "116.92" }
    ],
    "discounted": true,
    "discountAmount": 30,
    "stock": 586,
    "packagingSize": "",
    "packagingWeight": "Gewicht 6",
    "discontinued": false,
    "modelnumber": "54r12opklhdhl5tu",
    "_id": "645c9ffb7d433216f16d7c7a"
  },
  {
    "name": "Mikrowelle 177",
    "brand": "Samsung",
    "color": "Weiß",
    "size": "Größe 6",
    "weight": 45.71,
    "description": "Viel Platz",
    "category": "Mikrowelle",
    "prices": [
      { "validFrom": "07.05.2020", "validTo": "07.05.2021", "price": "262.55" },
      { "validFrom": "07.05.2021", "validTo": "07.05.2022", "price": "114.08" }
    ],
    "discounted": false,
    "discountAmount": 20,
    "stock": 693,
    "packagingSize": "",
    "packagingWeight": "Gewicht 6",
    "discontinued": false,
    "modelnumber": "54r12opklhdhl5tt",
    "_id": "645c9ffb7d433216f16d7c79"
  },
  {
    "name": "Trockner 176",
    "brand": "Bosch",
    "color": "Blau",
    "size": "Größe 6",
    "weight": 43.73,
    "description": "Viel Platz",
    "category": "Trockner",
    "prices": [
      { "validFrom": "07.05.2020", "validTo": "07.05.2021", "price": "935.29" },
      { "validFrom": "07.05.2021", "validTo": "07.05.2022", "price": "670.70" }
    ],
    "discounted": false,
    "discountAmount": 30,
    "stock": 687,
    "packagingSize": "",
    "packagingWeight": "Gewicht 4",
    "discontinued": false,
    "modelnumber": "54r12opklhdhl5ts",
    "_id": "645c9ffb7d433216f16d7c78"
  },
  {
    "name": "Kühlschrank 175",
    "brand": "LG",
    "color": "Weiß",
    "size": "Größe 7",
    "weight": 7.31,
    "description": "Hohe Energieeffizienz",
    "category": "Kühlschrank",
    "prices": [
      {
        "validFrom": "07.05.2020",
        "validTo": "07.05.2021",
        "price": "1408.57"
      },
      { "validFrom": "07.05.2021", "validTo": "07.05.2022", "price": "925.90" }
    ],
    "discounted": false,
    "discountAmount": 30,
    "stock": 6,
    "packagingSize": "",
    "packagingWeight": "Gewicht 2",
    "discontinued": false,
    "modelnumber": "54r12opklhdhl5tr",
    "_id": "645c9ffb7d433216f16d7c77"
  },
  {
    "name": "Kühlschrank 174",
    "brand": "Siemens",
    "color": "Silber",
    "size": "Größe 4",
    "weight": 44.03,
    "description": "Geräuscharm",
    "category": "Kühlschrank",
    "prices": [
      {
        "validFrom": "07.05.2020",
        "validTo": "07.05.2021",
        "price": "1181.43"
      },
      { "validFrom": "07.05.2021", "validTo": "07.05.2022", "price": "937.00" }
    ],
    "discounted": true,
    "discountAmount": 10,
    "stock": 985,
    "packagingSize": "",
    "packagingWeight": "Gewicht 8",
    "discontinued": false,
    "modelnumber": "54r12opklhdhl5tq",
    "_id": "645c9ffb7d433216f16d7c76"
  },
  {
    "name": "Ofen 173",
    "brand": "Miele",
    "color": "Blau",
    "size": "Größe 4",
    "weight": 14.2,
    "description": "Viel Platz",
    "category": "Ofen",
    "prices": [
      {
        "validFrom": "07.05.2020",
        "validTo": "07.05.2021",
        "price": "1020.64"
      },
      { "validFrom": "07.05.2021", "validTo": "07.05.2022", "price": "282.41" }
    ],
    "discounted": false,
    "discountAmount": 30,
    "stock": 818,
    "packagingSize": "",
    "packagingWeight": "Gewicht 7",
    "discontinued": false,
    "modelnumber": "54r12opklhdhl5tp",
    "_id": "645c9ffb7d433216f16d7c75"
  },
  {
    "name": "Kühlschrank 172",
    "brand": "Samsung",
    "color": "Schwarz",
    "size": "Größe 3",
    "weight": 24.55,
    "description": "Hohe Energieeffizienz",
    "category": "Kühlschrank",
    "prices": [
      { "validFrom": "07.05.2020", "validTo": "07.05.2021", "price": "819.94" },
      { "validFrom": "07.05.2021", "validTo": "07.05.2022", "price": "953.00" }
    ],
    "discounted": true,
    "discountAmount": 20,
    "stock": 968,
    "packagingSize": "",
    "packagingWeight": "Gewicht 8",
    "discontinued": false,
    "modelnumber": "54r12opklhdhl5to",
    "_id": "645c9ffb7d433216f16d7c74"
  },
  {
    "name": "Ofen 171",
    "brand": "AEG",
    "color": "Weiß",
    "size": "Größe 9",
    "weight": 48.92,
    "description": "Viel Platz",
    "category": "Ofen",
    "prices": [
      { "validFrom": "07.05.2020", "validTo": "07.05.2021", "price": "329.45" },
      { "validFrom": "07.05.2021", "validTo": "07.05.2022", "price": "782.56" }
    ],
    "discounted": true,
    "discountAmount": 30,
    "stock": 759,
    "packagingSize": "",
    "packagingWeight": "Gewicht 9",
    "discontinued": false,
    "modelnumber": "54r12opklhdhl5tn",
    "_id": "645c9ffb7d433216f16d7c73"
  },
  {
    "name": "Trockner 170",
    "brand": "Samsung",
    "color": "Rot",
    "size": "Größe 7",
    "weight": 29.94,
    "description": "Hohe Energieeffizienz",
    "category": "Trockner",
    "prices": [
      { "validFrom": "07.05.2020", "validTo": "07.05.2021", "price": "526.11" },
      { "validFrom": "07.05.2021", "validTo": "07.05.2022", "price": "326.84" }
    ],
    "discounted": true,
    "discountAmount": 30,
    "stock": 303,
    "packagingSize": "",
    "packagingWeight": "Gewicht 5",
    "discontinued": false,
    "modelnumber": "54r12opklhdhl5tm",
    "_id": "645c9ffb7d433216f16d7c72"
  },
  {
    "name": "Ofen 169",
    "brand": "Samsung",
    "color": "Silber",
    "size": "Größe 4",
    "weight": 44.13,
    "description": "Einfache Bedienung",
    "category": "Ofen",
    "prices": [
      {
        "validFrom": "07.05.2020",
        "validTo": "07.05.2021",
        "price": "1326.95"
      },
      { "validFrom": "07.05.2021", "validTo": "07.05.2022", "price": "368.92" }
    ],
    "discounted": true,
    "discountAmount": 10,
    "stock": 412,
    "packagingSize": "",
    "packagingWeight": "Gewicht 1",
    "discontinued": false,
    "modelnumber": "54r12opklhdhl5tl",
    "_id": "645c9ffb7d433216f16d7c71"
  },
  {
    "name": "Kühlschrank 168",
    "brand": "Bosch",
    "color": "Rot",
    "size": "Größe 3",
    "weight": 12.5,
    "description": "Einfache Bedienung",
    "category": "Kühlschrank",
    "prices": [
      { "validFrom": "07.05.2020", "validTo": "07.05.2021", "price": "475.97" },
      { "validFrom": "07.05.2021", "validTo": "07.05.2022", "price": "616.51" }
    ],
    "discounted": true,
    "discountAmount": 10,
    "stock": 834,
    "packagingSize": "",
    "packagingWeight": "Gewicht 3",
    "discontinued": false,
    "modelnumber": "54r12opklhdhl5tk",
    "_id": "645c9ffb7d433216f16d7c70"
  },
  {
    "name": "Waschmaschine 167",
    "brand": "Miele",
    "color": "Rot",
    "size": "Größe 2",
    "weight": 25.66,
    "description": "Hohe Energieeffizienz",
    "category": "Waschmaschine",
    "prices": [
      { "validFrom": "07.05.2020", "validTo": "07.05.2021", "price": "859.00" },
      { "validFrom": "07.05.2021", "validTo": "07.05.2022", "price": "447.00" }
    ],
    "discounted": true,
    "discountAmount": 30,
    "stock": 35,
    "packagingSize": "",
    "packagingWeight": "Gewicht 9",
    "discontinued": false,
    "modelnumber": "54r12opklhdhl5tj",
    "_id": "645c9ffb7d433216f16d7c6f"
  },
  {
    "name": "Waschmaschine 166",
    "brand": "Samsung",
    "color": "Blau",
    "size": "Größe 1",
    "weight": 22.05,
    "description": "Einfache Bedienung",
    "category": "Waschmaschine",
    "prices": [
      { "validFrom": "07.05.2020", "validTo": "07.05.2021", "price": "273.48" },
      { "validFrom": "07.05.2021", "validTo": "07.05.2022", "price": "437.19" }
    ],
    "discounted": true,
    "discountAmount": 30,
    "stock": 276,
    "packagingSize": "",
    "packagingWeight": "Gewicht 1",
    "discontinued": false,
    "modelnumber": "54r12opklhdhl5ti",
    "_id": "645c9ffb7d433216f16d7c6e"
  },
  {
    "name": "Waschmaschine 165",
    "brand": "Siemens",
    "color": "Schwarz",
    "size": "Größe 10",
    "weight": 17.74,
    "description": "Einfache Bedienung",
    "category": "Waschmaschine",
    "prices": [
      { "validFrom": "07.05.2020", "validTo": "07.05.2021", "price": "580.14" },
      { "validFrom": "07.05.2021", "validTo": "07.05.2022", "price": "945.01" }
    ],
    "discounted": true,
    "discountAmount": 10,
    "stock": 729,
    "packagingSize": "",
    "packagingWeight": "Gewicht 8",
    "discontinued": false,
    "modelnumber": "54r12opklhdhl5th",
    "_id": "645c9ffb7d433216f16d7c6d"
  },
  {
    "name": "Trockner 164",
    "brand": "Miele",
    "color": "Blau",
    "size": "Größe 7",
    "weight": 22.96,
    "description": "Viel Platz",
    "category": "Trockner",
    "prices": [
      { "validFrom": "07.05.2020", "validTo": "07.05.2021", "price": "473.24" },
      { "validFrom": "07.05.2021", "validTo": "07.05.2022", "price": "974.77" }
    ],
    "discounted": true,
    "discountAmount": 30,
    "stock": 21,
    "packagingSize": "",
    "packagingWeight": "Gewicht 6",
    "discontinued": false,
    "modelnumber": "54r12opklhdhl5tg",
    "_id": "645c9ffb7d433216f16d7c6c"
  },
  {
    "name": "Ofen 163",
    "brand": "Miele",
    "color": "Blau",
    "size": "Größe 1",
    "weight": 10.27,
    "description": "Viel Platz",
    "category": "Ofen",
    "prices": [
      { "validFrom": "07.05.2020", "validTo": "07.05.2021", "price": "527.57" },
      { "validFrom": "07.05.2021", "validTo": "07.05.2022", "price": "166.08" }
    ],
    "discounted": true,
    "discountAmount": 10,
    "stock": 155,
    "packagingSize": "",
    "packagingWeight": "Gewicht 2",
    "discontinued": false,
    "modelnumber": "54r12opklhdhl5tf",
    "_id": "645c9ffb7d433216f16d7c6b"
  },
  {
    "name": "Ofen 162",
    "brand": "Samsung",
    "color": "Rot",
    "size": "Größe 1",
    "weight": 19.69,
    "description": "Hohe Energieeffizienz",
    "category": "Ofen",
    "prices": [
      { "validFrom": "07.05.2020", "validTo": "07.05.2021", "price": "337.19" },
      { "validFrom": "07.05.2021", "validTo": "07.05.2022", "price": "459.30" }
    ],
    "discounted": true,
    "discountAmount": 10,
    "stock": 566,
    "packagingSize": "",
    "packagingWeight": "Gewicht 8",
    "discontinued": false,
    "modelnumber": "54r12opklhdhl5te",
    "_id": "645c9ffb7d433216f16d7c6a"
  },
  {
    "name": "Geschirrspüler 161",
    "brand": "AEG",
    "color": "Weiß",
    "size": "Größe 6",
    "weight": 23.57,
    "description": "Hohe Energieeffizienz",
    "category": "Geschirrspüler",
    "prices": [
      { "validFrom": "07.05.2020", "validTo": "07.05.2021", "price": "690.26" },
      { "validFrom": "07.05.2021", "validTo": "07.05.2022", "price": "586.31" }
    ],
    "discounted": true,
    "discountAmount": 10,
    "stock": 6,
    "packagingSize": "",
    "packagingWeight": "Gewicht 5",
    "discontinued": false,
    "modelnumber": "54r12opklhdhl5td",
    "_id": "645c9ffb7d433216f16d7c69"
  },
  {
    "name": "Trockner 160",
    "brand": "Miele",
    "color": "Schwarz",
    "size": "Größe 7",
    "weight": 37.72,
    "description": "Geräuscharm",
    "category": "Trockner",
    "prices": [
      { "validFrom": "07.05.2020", "validTo": "07.05.2021", "price": "472.78" },
      { "validFrom": "07.05.2021", "validTo": "07.05.2022", "price": "643.35" }
    ],
    "discounted": false,
    "discountAmount": 30,
    "stock": 425,
    "packagingSize": "",
    "packagingWeight": "Gewicht 2",
    "discontinued": false,
    "modelnumber": "54r12opklhdhl5tc",
    "_id": "645c9ffb7d433216f16d7c68"
  },
  {
    "name": "Ofen 159",
    "brand": "Samsung",
    "color": "Silber",
    "size": "Größe 7",
    "weight": 11.9,
    "description": "Geräuscharm",
    "category": "Ofen",
    "prices": [
      {
        "validFrom": "07.05.2020",
        "validTo": "07.05.2021",
        "price": "1107.70"
      },
      { "validFrom": "07.05.2021", "validTo": "07.05.2022", "price": "719.33" }
    ],
    "discounted": false,
    "discountAmount": 20,
    "stock": 430,
    "packagingSize": "",
    "packagingWeight": "Gewicht 10",
    "discontinued": false,
    "modelnumber": "54r12opklhdhl5tb",
    "_id": "645c9ffb7d433216f16d7c67"
  },
  {
    "name": "Trockner 158",
    "brand": "LG",
    "color": "Weiß",
    "size": "Größe 6",
    "weight": 4.27,
    "description": "Hohe Energieeffizienz",
    "category": "Trockner",
    "prices": [
      {
        "validFrom": "07.05.2020",
        "validTo": "07.05.2021",
        "price": "1094.45"
      },
      { "validFrom": "07.05.2021", "validTo": "07.05.2022", "price": "385.63" }
    ],
    "discounted": false,
    "discountAmount": 30,
    "stock": 703,
    "packagingSize": "",
    "packagingWeight": "Gewicht 4",
    "discontinued": false,
    "modelnumber": "54r12opklhdhl5ta",
    "_id": "645c9ffb7d433216f16d7c66"
  },
  {
    "name": "Ofen 157",
    "brand": "Miele",
    "color": "Silber",
    "size": "Größe 7",
    "weight": 14.41,
    "description": "Einfache Bedienung",
    "category": "Ofen",
    "prices": [
      { "validFrom": "07.05.2020", "validTo": "07.05.2021", "price": "839.20" },
      { "validFrom": "07.05.2021", "validTo": "07.05.2022", "price": "746.37" }
    ],
    "discounted": true,
    "discountAmount": 30,
    "stock": 464,
    "packagingSize": "",
    "packagingWeight": "Gewicht 8",
    "discontinued": false,
    "modelnumber": "54r12opklhdhl5t9",
    "_id": "645c9ffb7d433216f16d7c65"
  },
  {
    "name": "Trockner 156",
    "brand": "Siemens",
    "color": "Blau",
    "size": "Größe 2",
    "weight": 32.67,
    "description": "Einfache Bedienung",
    "category": "Trockner",
    "prices": [
      { "validFrom": "07.05.2020", "validTo": "07.05.2021", "price": "358.28" },
      { "validFrom": "07.05.2021", "validTo": "07.05.2022", "price": "836.56" }
    ],
    "discounted": false,
    "discountAmount": 10,
    "stock": 874,
    "packagingSize": "",
    "packagingWeight": "Gewicht 10",
    "discontinued": false,
    "modelnumber": "54r12opklhdhl5t8",
    "_id": "645c9ffb7d433216f16d7c64"
  },
  {
    "name": "Geschirrspüler 155",
    "brand": "LG",
    "color": "Silber",
    "size": "Größe 6",
    "weight": 2.7,
    "description": "Einfache Bedienung",
    "category": "Geschirrspüler",
    "prices": [
      { "validFrom": "07.05.2020", "validTo": "07.05.2021", "price": "702.83" },
      { "validFrom": "07.05.2021", "validTo": "07.05.2022", "price": "431.82" }
    ],
    "discounted": false,
    "discountAmount": 20,
    "stock": 657,
    "packagingSize": "",
    "packagingWeight": "Gewicht 8",
    "discontinued": false,
    "modelnumber": "54r12opklhdhl5t7",
    "_id": "645c9ffb7d433216f16d7c63"
  },
  {
    "name": "Trockner 154",
    "brand": "Miele",
    "color": "Blau",
    "size": "Größe 8",
    "weight": 9.78,
    "description": "Geräuscharm",
    "category": "Trockner",
    "prices": [
      { "validFrom": "07.05.2020", "validTo": "07.05.2021", "price": "393.52" },
      { "validFrom": "07.05.2021", "validTo": "07.05.2022", "price": "264.41" }
    ],
    "discounted": false,
    "discountAmount": 30,
    "stock": 218,
    "packagingSize": "",
    "packagingWeight": "Gewicht 6",
    "discontinued": false,
    "modelnumber": "54r12opklhdhl5t6",
    "_id": "645c9ffb7d433216f16d7c62"
  },
  {
    "name": "Mikrowelle 153",
    "brand": "Siemens",
    "color": "Schwarz",
    "size": "Größe 10",
    "weight": 27.63,
    "description": "Viel Platz",
    "category": "Mikrowelle",
    "prices": [
      { "validFrom": "07.05.2020", "validTo": "07.05.2021", "price": "870.78" },
      { "validFrom": "07.05.2021", "validTo": "07.05.2022", "price": "485.71" }
    ],
    "discounted": true,
    "discountAmount": 10,
    "stock": 457,
    "packagingSize": "",
    "packagingWeight": "Gewicht 6",
    "discontinued": false,
    "modelnumber": "54r12opklhdhl5t5",
    "_id": "645c9ffb7d433216f16d7c61"
  },
  {
    "name": "Waschmaschine 152",
    "brand": "Miele",
    "color": "Schwarz",
    "size": "Größe 2",
    "weight": 28.52,
    "description": "Geräuscharm",
    "category": "Waschmaschine",
    "prices": [
      {
        "validFrom": "07.05.2020",
        "validTo": "07.05.2021",
        "price": "1151.78"
      },
      { "validFrom": "07.05.2021", "validTo": "07.05.2022", "price": "591.89" }
    ],
    "discounted": true,
    "discountAmount": 10,
    "stock": 926,
    "packagingSize": "",
    "packagingWeight": "Gewicht 2",
    "discontinued": false,
    "modelnumber": "54r12opklhdhl5t4",
    "_id": "645c9ffb7d433216f16d7c60"
  },
  {
    "name": "Geschirrspüler 151",
    "brand": "Bosch",
    "color": "Weiß",
    "size": "Größe 2",
    "weight": 40.92,
    "description": "Viel Platz",
    "category": "Geschirrspüler",
    "prices": [
      {
        "validFrom": "07.05.2020",
        "validTo": "07.05.2021",
        "price": "1265.37"
      },
      { "validFrom": "07.05.2021", "validTo": "07.05.2022", "price": "304.86" }
    ],
    "discounted": true,
    "discountAmount": 10,
    "stock": 492,
    "packagingSize": "",
    "packagingWeight": "Gewicht 3",
    "discontinued": false,
    "modelnumber": "54r12opklhdhl5t3",
    "_id": "645c9ffb7d433216f16d7c5f"
  },
  {
    "name": "Ofen 150",
    "brand": "Miele",
    "color": "Schwarz",
    "size": "Größe 5",
    "weight": 35.01,
    "description": "Einfache Bedienung",
    "category": "Ofen",
    "prices": [
      { "validFrom": "07.05.2020", "validTo": "07.05.2021", "price": "962.54" },
      { "validFrom": "07.05.2021", "validTo": "07.05.2022", "price": "792.57" }
    ],
    "discounted": false,
    "discountAmount": 30,
    "stock": 446,
    "packagingSize": "",
    "packagingWeight": "Gewicht 5",
    "discontinued": false,
    "modelnumber": "54r12opklhdhl5t2",
    "_id": "645c9ffb7d433216f16d7c5e"
  },
  {
    "name": "Ofen 149",
    "brand": "Bosch",
    "color": "Schwarz",
    "size": "Größe 4",
    "weight": 4.95,
    "description": "Viel Platz",
    "category": "Ofen",
    "prices": [
      { "validFrom": "07.05.2020", "validTo": "07.05.2021", "price": "536.48" },
      { "validFrom": "07.05.2021", "validTo": "07.05.2022", "price": "972.43" }
    ],
    "discounted": false,
    "discountAmount": 20,
    "stock": 290,
    "packagingSize": "",
    "packagingWeight": "Gewicht 2",
    "discontinued": false,
    "modelnumber": "54r12opklhdhl5t1",
    "_id": "645c9ffb7d433216f16d7c5d"
  },
  {
    "name": "Ofen 148",
    "brand": "Bosch",
    "color": "Rot",
    "size": "Größe 2",
    "weight": 22.78,
    "description": "Viel Platz",
    "category": "Ofen",
    "prices": [
      { "validFrom": "07.05.2020", "validTo": "07.05.2021", "price": "732.32" },
      { "validFrom": "07.05.2021", "validTo": "07.05.2022", "price": "259.34" }
    ],
    "discounted": false,
    "discountAmount": 10,
    "stock": 440,
    "packagingSize": "",
    "packagingWeight": "Gewicht 8",
    "discontinued": false,
    "modelnumber": "54r12opklhdhl5t0",
    "_id": "645c9ffb7d433216f16d7c5c"
  },
  {
    "name": "Trockner 147",
    "brand": "AEG",
    "color": "Silber",
    "size": "Größe 4",
    "weight": 6.02,
    "description": "Hohe Energieeffizienz",
    "category": "Trockner",
    "prices": [
      {
        "validFrom": "07.05.2020",
        "validTo": "07.05.2021",
        "price": "1075.06"
      },
      { "validFrom": "07.05.2021", "validTo": "07.05.2022", "price": "974.73" }
    ],
    "discounted": false,
    "discountAmount": 30,
    "stock": 277,
    "packagingSize": "",
    "packagingWeight": "Gewicht 1",
    "discontinued": false,
    "modelnumber": "54r12opklhdhl5sz",
    "_id": "645c9ffb7d433216f16d7c5b"
  },
  {
    "name": "Kühlschrank 146",
    "brand": "Siemens",
    "color": "Weiß",
    "size": "Größe 10",
    "weight": 10.86,
    "description": "Einfache Bedienung",
    "category": "Kühlschrank",
    "prices": [
      {
        "validFrom": "07.05.2020",
        "validTo": "07.05.2021",
        "price": "1455.32"
      },
      { "validFrom": "07.05.2021", "validTo": "07.05.2022", "price": "423.84" }
    ],
    "discounted": false,
    "discountAmount": 10,
    "stock": 610,
    "packagingSize": "",
    "packagingWeight": "Gewicht 10",
    "discontinued": false,
    "modelnumber": "54r12opklhdhl5sy",
    "_id": "645c9ffb7d433216f16d7c5a"
  },
  {
    "name": "Ofen 145",
    "brand": "Bosch",
    "color": "Weiß",
    "size": "Größe 3",
    "weight": 48.51,
    "description": "Hohe Energieeffizienz",
    "category": "Ofen",
    "prices": [
      {
        "validFrom": "07.05.2020",
        "validTo": "07.05.2021",
        "price": "1041.63"
      },
      { "validFrom": "07.05.2021", "validTo": "07.05.2022", "price": "437.21" }
    ],
    "discounted": true,
    "discountAmount": 20,
    "stock": 839,
    "packagingSize": "",
    "packagingWeight": "Gewicht 8",
    "discontinued": false,
    "modelnumber": "54r12opklhdhl5sx",
    "_id": "645c9ffb7d433216f16d7c59"
  },
  {
    "name": "Kühlschrank 144",
    "brand": "AEG",
    "color": "Schwarz",
    "size": "Größe 1",
    "weight": 14.16,
    "description": "Hohe Energieeffizienz",
    "category": "Kühlschrank",
    "prices": [
      { "validFrom": "07.05.2020", "validTo": "07.05.2021", "price": "500.31" },
      { "validFrom": "07.05.2021", "validTo": "07.05.2022", "price": "785.44" }
    ],
    "discounted": true,
    "discountAmount": 10,
    "stock": 409,
    "packagingSize": "",
    "packagingWeight": "Gewicht 2",
    "discontinued": false,
    "modelnumber": "54r12opklhdhl5sw",
    "_id": "645c9ffb7d433216f16d7c58"
  },
  {
    "name": "Waschmaschine 143",
    "brand": "AEG",
    "color": "Silber",
    "size": "Größe 4",
    "weight": 33.82,
    "description": "Einfache Bedienung",
    "category": "Waschmaschine",
    "prices": [
      { "validFrom": "07.05.2020", "validTo": "07.05.2021", "price": "551.50" },
      { "validFrom": "07.05.2021", "validTo": "07.05.2022", "price": "491.30" }
    ],
    "discounted": true,
    "discountAmount": 20,
    "stock": 678,
    "packagingSize": "",
    "packagingWeight": "Gewicht 4",
    "discontinued": false,
    "modelnumber": "54r12opklhdhl5sv",
    "_id": "645c9ffb7d433216f16d7c57"
  },
  {
    "name": "Ofen 142",
    "brand": "Bosch",
    "color": "Rot",
    "size": "Größe 3",
    "weight": 28.62,
    "description": "Einfache Bedienung",
    "category": "Ofen",
    "prices": [
      {
        "validFrom": "07.05.2020",
        "validTo": "07.05.2021",
        "price": "1187.11"
      },
      { "validFrom": "07.05.2021", "validTo": "07.05.2022", "price": "332.48" }
    ],
    "discounted": true,
    "discountAmount": 10,
    "stock": 617,
    "packagingSize": "",
    "packagingWeight": "Gewicht 9",
    "discontinued": false,
    "modelnumber": "54r12opklhdhl5su",
    "_id": "645c9ffb7d433216f16d7c56"
  },
  {
    "name": "Geschirrspüler 141",
    "brand": "Siemens",
    "color": "Rot",
    "size": "Größe 8",
    "weight": 28.54,
    "description": "Einfache Bedienung",
    "category": "Geschirrspüler",
    "prices": [
      { "validFrom": "07.05.2020", "validTo": "07.05.2021", "price": "289.60" },
      { "validFrom": "07.05.2021", "validTo": "07.05.2022", "price": "818.54" }
    ],
    "discounted": false,
    "discountAmount": 20,
    "stock": 904,
    "packagingSize": "",
    "packagingWeight": "Gewicht 7",
    "discontinued": false,
    "modelnumber": "54r12opklhdhl5st",
    "_id": "645c9ffb7d433216f16d7c55"
  },
  {
    "name": "Kühlschrank 140",
    "brand": "AEG",
    "color": "Weiß",
    "size": "Größe 7",
    "weight": 14.63,
    "description": "Geräuscharm",
    "category": "Kühlschrank",
    "prices": [
      { "validFrom": "07.05.2020", "validTo": "07.05.2021", "price": "394.96" },
      { "validFrom": "07.05.2021", "validTo": "07.05.2022", "price": "701.34" }
    ],
    "discounted": true,
    "discountAmount": 10,
    "stock": 106,
    "packagingSize": "",
    "packagingWeight": "Gewicht 8",
    "discontinued": false,
    "modelnumber": "54r12opklhdhl5ss",
    "_id": "645c9ffb7d433216f16d7c54"
  },
  {
    "name": "Ofen 139",
    "brand": "LG",
    "color": "Rot",
    "size": "Größe 5",
    "weight": 14.18,
    "description": "Viel Platz",
    "category": "Ofen",
    "prices": [
      {
        "validFrom": "07.05.2020",
        "validTo": "07.05.2021",
        "price": "1434.13"
      },
      { "validFrom": "07.05.2021", "validTo": "07.05.2022", "price": "994.06" }
    ],
    "discounted": true,
    "discountAmount": 20,
    "stock": 879,
    "packagingSize": "",
    "packagingWeight": "Gewicht 6",
    "discontinued": false,
    "modelnumber": "54r12opklhdhl5sr",
    "_id": "645c9ffb7d433216f16d7c53"
  },
  {
    "name": "Trockner 138",
    "brand": "Bosch",
    "color": "Schwarz",
    "size": "Größe 8",
    "weight": 26.08,
    "description": "Hohe Energieeffizienz",
    "category": "Trockner",
    "prices": [
      { "validFrom": "07.05.2020", "validTo": "07.05.2021", "price": "381.51" },
      { "validFrom": "07.05.2021", "validTo": "07.05.2022", "price": "607.16" }
    ],
    "discounted": true,
    "discountAmount": 10,
    "stock": 280,
    "packagingSize": "",
    "packagingWeight": "Gewicht 2",
    "discontinued": false,
    "modelnumber": "54r12opklhdhl5sq",
    "_id": "645c9ffb7d433216f16d7c52"
  },
  {
    "name": "Kühlschrank 137",
    "brand": "Samsung",
    "color": "Silber",
    "size": "Größe 3",
    "weight": 28.93,
    "description": "Hohe Energieeffizienz",
    "category": "Kühlschrank",
    "prices": [
      {
        "validFrom": "07.05.2020",
        "validTo": "07.05.2021",
        "price": "1122.79"
      },
      { "validFrom": "07.05.2021", "validTo": "07.05.2022", "price": "774.33" }
    ],
    "discounted": false,
    "discountAmount": 30,
    "stock": 167,
    "packagingSize": "",
    "packagingWeight": "Gewicht 2",
    "discontinued": false,
    "modelnumber": "54r12opklhdhl5sp",
    "_id": "645c9ffb7d433216f16d7c51"
  },
  {
    "name": "Ofen 136",
    "brand": "Miele",
    "color": "Blau",
    "size": "Größe 8",
    "weight": 32.04,
    "description": "Hohe Energieeffizienz",
    "category": "Ofen",
    "prices": [
      { "validFrom": "07.05.2020", "validTo": "07.05.2021", "price": "671.25" },
      { "validFrom": "07.05.2021", "validTo": "07.05.2022", "price": "985.47" }
    ],
    "discounted": true,
    "discountAmount": 20,
    "stock": 409,
    "packagingSize": "",
    "packagingWeight": "Gewicht 10",
    "discontinued": false,
    "modelnumber": "54r12opklhdhl5so",
    "_id": "645c9ffb7d433216f16d7c50"
  },
  {
    "name": "Geschirrspüler 135",
    "brand": "Samsung",
    "color": "Weiß",
    "size": "Größe 4",
    "weight": 44.31,
    "description": "Geräuscharm",
    "category": "Geschirrspüler",
    "prices": [
      { "validFrom": "07.05.2020", "validTo": "07.05.2021", "price": "600.75" },
      { "validFrom": "07.05.2021", "validTo": "07.05.2022", "price": "107.16" }
    ],
    "discounted": false,
    "discountAmount": 20,
    "stock": 424,
    "packagingSize": "",
    "packagingWeight": "Gewicht 8",
    "discontinued": false,
    "modelnumber": "54r12opklhdhl5sn",
    "_id": "645c9ffb7d433216f16d7c4f"
  }
]
